quick_topic/__init__.py
quick_topic/cli.py
quick_topic/__pycache__/__init__.cpython-36.pyc
quick_topic/__pycache__/__init__.cpython-39.pyc
quick_topic/__pycache__/cli.cpython-36.pyc
quick_topic/__pycache__/cli.cpython-39.pyc
quick_topic/gui/__init__.py
quick_topic/gui/main.py
quick_topic/gui/main.ui
quick_topic/gui/qtt.png
quick_topic/gui/quick_topic.config
quick_topic/gui/run.py
quick_topic/gui/__pycache__/__init__.cpython-36.pyc
quick_topic/gui/__pycache__/__init__.cpython-39.pyc
quick_topic/gui/__pycache__/main.cpython-36.pyc
quick_topic/gui/__pycache__/main.cpython-39.pyc
quick_topic/gui/__pycache__/run.cpython-36.pyc
quick_topic/gui/__pycache__/run.cpython-39.pyc
quick_topic/gui_functions/__init__.py
quick_topic/gui_functions/gui_keywordstat.py
quick_topic/gui_functions/gui_topic_explore.py
quick_topic/gui_functions/gui_topic_interaction.py
quick_topic/gui_functions/gui_topic_modeling.py
quick_topic/gui_functions/gui_topic_prevalence.py
quick_topic/gui_functions/gui_topic_similarity.py
quick_topic/gui_functions/gui_topic_transition_term_year.py
quick_topic/gui_functions/gui_topic_transition_topic_year.py
quick_topic/gui_functions/gui_topic_trends.py
quick_topic/gui_functions/gui_topic_trends_correlation.py
quick_topic/gui_functions/__pycache__/__init__.cpython-36.pyc
quick_topic/gui_functions/__pycache__/__init__.cpython-39.pyc
quick_topic/gui_functions/__pycache__/gui_keywordstat.cpython-36.pyc
quick_topic/gui_functions/__pycache__/gui_keywordstat.cpython-39.pyc
quick_topic/gui_functions/__pycache__/gui_topic_explore.cpython-39.pyc
quick_topic/gui_functions/__pycache__/gui_topic_interaction.cpython-36.pyc
quick_topic/gui_functions/__pycache__/gui_topic_interaction.cpython-39.pyc
quick_topic/gui_functions/__pycache__/gui_topic_modeling.cpython-36.pyc
quick_topic/gui_functions/__pycache__/gui_topic_modeling.cpython-39.pyc
quick_topic/gui_functions/__pycache__/gui_topic_prevalence.cpython-36.pyc
quick_topic-1.0.2.dist-info/LICENSE
quick_topic-1.0.2.dist-info/METADATA
quick_topic-1.0.2.dist-info/WHEEL
quick_topic-1.0.2.dist-info/entry_points.txt
quick_topic-1.0.2.dist-info/top_level.txt
quick_topic-1.0.2.dist-info/RECORD
