Metadata-Version: 2.1
Name: quick-topic
Version: 1.0.2
Summary: A toolkit to quickly analyze topic models using various methods
Home-page: https://github.com/dhchenx/quick-topic
Author: Donghua Chen
Author-email: douglaschan@126.com
License: MIT
Project-URL: Bug Reports, https://github.com/dhchenx/quick-topic/issues
Project-URL: Source, https://github.com/dhchenx/quick-topic
Keywords: topic mining,text analysis
Classifier: Development Status :: 5 - Production/Stable
Classifier: Intended Audience :: Developers
Classifier: Topic :: Software Development :: Build Tools
Classifier: License :: OSI Approved :: MIT License
Classifier: Programming Language :: Python :: 3
Classifier: Programming Language :: Python :: 3.6
Classifier: Programming Language :: Python :: 3.7
Classifier: Programming Language :: Python :: 3.8
Classifier: Programming Language :: Python :: 3.9
Classifier: Programming Language :: Python :: 3 :: Only
Requires-Python: >=3.6, <4
License-File: LICENSE
Requires-Dist: jieba
Requires-Dist: quick-csv
Requires-Dist: gensim
Requires-Dist: numpy
Requires-Dist: pandas
Requires-Dist: matplotlib
Requires-Dist: correlation-kit
Requires-Dist: strsimpy
Requires-Dist: PyQt5
Requires-Dist: pyqtgraph
Requires-Dist: spacy
Requires-Dist: wordcloud
Requires-Dist: seaborn
Requires-Dist: sklearn
Requires-Dist: bokeh
Requires-Dist: pyLDAvis
Provides-Extra: dev
Requires-Dist: check-manifest ; extra == 'dev'
Provides-Extra: test
Requires-Dist: coverage ; extra == 'test'
